<?xml version="1.0" encoding="UTF-8" standalone="yes"?>


<item>
<title>S07E01 - Rocadrag칩n</title>
<link>
<sublink>https://docs.google.com/file/d/  /preview</sublink>
<sublink>http://198.27.75.154/cosmeticos/series4K/GAMES%20OF%20THRONES%204K%20DUAL%20AUDIO/TEMPORADA7/Game%20of%20Thrones%20S07E01.4K.trial-claucha75.mkv</sublink>
</link>
<thumbnail></thumbnail>
<fanart></fanart>
</item>

<item>
<title>S07E02 - Bajo la Tormenta</title>
<link>
<sublink>https://docs.google.com/file/d/  /preview</sublink>
<sublink>http://198.27.75.154/cosmeticos/series4K/GAMES%20OF%20THRONES%204K%20DUAL%20AUDIO/TEMPORADA7/Game%20of%20Thrones%20S07E02.4K.trial-claucha75.mkv</sublink>
</link>
<thumbnail></thumbnail>
<fanart></fanart>
</item>

<item>
<title>S07E03 - La Justicia de la Reina</title>
<link>
<sublink>https://docs.google.com/file/d/  /preview</sublink>
<sublink>http://198.27.75.154/cosmeticos/series4K/GAMES%20OF%20THRONES%204K%20DUAL%20AUDIO/TEMPORADA7/Game%20of%20Thrones%20S07E03.4K.trial-claucha75.mkv</sublink>
</link>
<thumbnail></thumbnail>
<fanart></fanart>
</item>

<item>
<title>S07E04 - Botines de Guerra</title>
<link>
<sublink>https://docs.google.com/file/d/  /preview</sublink>
<sublink>http://198.27.75.154/cosmeticos/series4K/GAMES%20OF%20THRONES%204K%20DUAL%20AUDIO/TEMPORADA7/Game%20of%20Thrones%20S07E04.4K.trial-claucha75.mkv</sublink>
</link>
<thumbnail></thumbnail>
<fanart></fanart>
</item>

<item>
<title>S07E05 - Guardiaoriente</title>
<link>
<sublink>https://docs.google.com/file/d/  /preview</sublink>
<sublink>http://198.27.75.154/cosmeticos/series4K/GAMES%20OF%20THRONES%204K%20DUAL%20AUDIO/TEMPORADA7/Game%20of%20Thrones%20S07E05.4K.trial-claucha75.mkv</sublink>
</link>
<thumbnail></thumbnail>
<fanart></fanart>
</item>

<item>
<title>S07E06 - M치s all치 del Muro</title>
<link>
<sublink>https://docs.google.com/file/d/  /preview</sublink>
<sublink>http://198.27.75.154/cosmeticos/series4K/GAMES%20OF%20THRONES%204K%20DUAL%20AUDIO/TEMPORADA7/Game%20of%20Thrones%20S07E06.4K.trial-claucha75.mkv</sublink>
</link>
<thumbnail></thumbnail>
<fanart></fanart>
</item>

<item>
<title>S07E07 - El Drag칩n y el Lobo</title>
<link>
<sublink>https://docs.google.com/file/d/  /preview</sublink>
<sublink>http://198.27.75.154/cosmeticos/series4K/GAMES%20OF%20THRONES%204K%20DUAL%20AUDIO/TEMPORADA7/Game%20of%20Thrones%20S07E07.4K.trial-claucha75.mkv</sublink>
</link>
<thumbnail></thumbnail>
<fanart></fanart>
</item>