<?xml version="1.0" encoding="UTF-8" standalone="yes"?>

<item>
<title>Cómo conocí a tu Madre S09E01 - El medallón</title>
<link>
<sublink>https://docs.google.com/file/d/   /preview</sublink>
</link>
<thumbnail></thumbnail>
<fanart></fanart>
</item>

<item>
<title>Cómo conocí a tu Madre S09E02 - El regreso</title>
<link>
<sublink>https://docs.google.com/file/d/   /preview</sublink>
</link>
<thumbnail></thumbnail>
<fanart></fanart>
</item>

<item>
<title>Cómo conocí a tu Madre S09E03 - La última noche en Nueva York</title>
<link>
<sublink>https://docs.google.com/file/d/   /preview</sublink>
</link>
<thumbnail></thumbnail>
<fanart></fanart>
</item>

<item>
<title>Cómo conocí a tu Madre S09E04 - La infracción del código</title>
<link>
<sublink>https://docs.google.com/file/d/   /preview</sublink>
</link>
<thumbnail></thumbnail>
<fanart></fanart>
</item>

<item>
<title>Cómo conocí a tu Madre S09E05 - La partida de póker</title>
<link>
<sublink>https://docs.google.com/file/d/   /preview</sublink>
</link>
<thumbnail></thumbnail>
<fanart></fanart>
</item>

<item>
<title>Cómo conocí a tu Madre S09E06 - Caballeros templarios</title>
<link>
<sublink>https://docs.google.com/file/d/   /preview</sublink>
</link>
<thumbnail></thumbnail>
<fanart></fanart>
</item>

<item>
<title>Cómo conocí a tu Madre S09E07 - Nada de preguntas</title>
<link>
<sublink>https://docs.google.com/file/d/   /preview</sublink>
</link>
<thumbnail></thumbnail>
<fanart></fanart>
</item>

<item>
<title>Cómo conocí a tu Madre S09E08 - El faro</title>
<link>
<sublink>https://docs.google.com/file/d/   /preview</sublink>
</link>
<thumbnail></thumbnail>
<fanart></fanart>
</item>

<item>
<title>Cómo conocí a tu Madre S09E09 - Aplatonicado</title>
<link>
<sublink>https://docs.google.com/file/d/   /preview</sublink>
</link>
<thumbnail></thumbnail>
<fanart></fanart>
</item>

<item>
<title>Cómo conocí a tu Madre S09E10 - Mamá y papá</title>
<link>
<sublink>https://docs.google.com/file/d/   /preview</sublink>
</link>
<thumbnail></thumbnail>
<fanart></fanart>
</item>

<item>
<title>Cómo conocí a tu Madre S09E11 - Historias para dormir</title>
<link>
<sublink>https://docs.google.com/file/d/   /preview</sublink>
</link>
<thumbnail></thumbnail>
<fanart></fanart>
</item>

<item>
<title>Cómo conocí a tu Madre S09E12 - La cena de ensayo</title>
<link>
<sublink>https://docs.google.com/file/d/   /preview</sublink>
</link>
<thumbnail></thumbnail>
<fanart></fanart>
</item>

<item>
<title>Cómo conocí a tu Madre S09E13 - Se busca bajista</title>
<link>
<sublink>https://docs.google.com/file/d/   /preview</sublink>
</link>
<thumbnail></thumbnail>
<fanart></fanart>
</item>

<item>
<title>Cómo conocí a tu Madre S09E14 - Acción de tortas 3 Boficita en Bofetilandia</title>
<link>
<sublink>https://docs.google.com/file/d/   /preview</sublink>
</link>
<thumbnail></thumbnail>
<fanart></fanart>
</item>

<item>
<title>Cómo conocí a tu Madre S09E15 - Fuera pausa</title>
<link>
<sublink>https://docs.google.com/file/d/   /preview</sublink>
</link>
<thumbnail></thumbnail>
<fanart></fanart>
</item>

<item>
<title>Cómo conocí a tu Madre S09E16 - Cómo me conoció vuestra madre</title>
<link>
<sublink>https://docs.google.com/file/d/   /preview</sublink>
</link>
<thumbnail></thumbnail>
<fanart></fanart>
</item>

<item>
<title>Cómo conocí a tu Madre S09E17 - Amanecer</title>
<link>
<sublink>https://docs.google.com/file/d/   /preview</sublink>
</link>
<thumbnail></thumbnail>
<fanart></fanart>
</item>

<item>
<title>Cómo conocí a tu Madre S09E18 - Levantar cabeza</title>
<link>
<sublink>https://docs.google.com/file/d/   /preview</sublink>
</link>
<thumbnail></thumbnail>
<fanart></fanart>
</item>

<item>
<title>Cómo conocí a tu Madre S09E19 - Vesubio</title>
<link>
<sublink>https://docs.google.com/file/d/   /preview</sublink>
</link>
<thumbnail></thumbnail>
<fanart></fanart>
</item>

<item>
<title>Cómo conocí a tu Madre S09E20 - Margarita</title>
<link>
<sublink>https://docs.google.com/file/d/   /preview</sublink>
</link>
<thumbnail></thumbnail>
<fanart></fanart>
</item>

<item>
<title>Cómo conocí a tu Madre S09E21 - Gary Blauman</title>
<link>
<sublink>https://docs.google.com/file/d/   /preview</sublink>
</link>
<thumbnail></thumbnail>
<fanart></fanart>
</item>

<item>
<title>Cómo conocí a tu Madre S09E22 - El camino al altar</title>
<link>
<sublink>https://docs.google.com/file/d/   /preview</sublink>
</link>
<thumbnail></thumbnail>
<fanart></fanart>
</item>

<item>
<title>Cómo conocí a tu Madre S09E23 - Juntos para siempre (1)</title>
<link>
<sublink>https://docs.google.com/file/d/   /preview</sublink>
</link>
<thumbnail></thumbnail>
<fanart></fanart>
</item>

<item>
<title>Cómo conocí a tu Madre S09E24 - Juntos para siempre (1)</title>
<link>
<sublink>https://docs.google.com/file/d/   /preview</sublink>
</link>
<thumbnail></thumbnail>
<fanart></fanart>
</item>